pytweet/__init__.py
pytweet/__main__.py
pytweet/attachments.py
pytweet/auth.py
pytweet/client.py
pytweet/entities.py
pytweet/enums.py
pytweet/errors.py
pytweet/http.py
pytweet/message.py
pytweet/metrics.py
pytweet/py.typed
pytweet/ratelimithandler.py
pytweet/relations.py
pytweet/tweet.py
pytweet/user.py
pytweet/utils.py
PyTweet-1.2.0.dist-info/LICENSE
PyTweet-1.2.0.dist-info/METADATA
PyTweet-1.2.0.dist-info/WHEEL
PyTweet-1.2.0.dist-info/top_level.txt
PyTweet-1.2.0.dist-info/RECORD
