Metadata-Version: 2.1
Name: PyTweet
Version: 1.2.0
Summary: A Synchronous python API wrapper for twitter's api
Home-page: https://github.com/TheFarGG/PyTweet/
Author: TheGenocide & TheFarGG
Maintainer: TheFarGG, TheGenocide
License: MIT
Project-URL: Documentation, https://py-tweet.readthedocs.io/
Project-URL: HomePage/Github, https://github.com/TheFarGG/PyTweet/
Keywords: PyTweet,pytweet,twitter,tweet.py twitter.py
Platform: UNKNOWN
Classifier: License :: OSI Approved :: MIT License
Classifier: Programming Language :: Python :: 3.7
Classifier: Programming Language :: Python :: 3.8
Classifier: Programming Language :: Python :: 3.9
Classifier: Programming Language :: Python :: 3.10
Classifier: Operating System :: OS Independent
Classifier: Topic :: Internet
Classifier: Topic :: Utilities
Classifier: Development Status :: 5 - Production/Stable
Requires-Python: >=3.7.0
Requires-Dist: requests
Requires-Dist: requests-oauthlib
Requires-Dist: python-dateutil
Provides-Extra: docs
Requires-Dist: sphinx-rtd-dark-mode (==1.2.4) ; extra == 'docs'
Requires-Dist: furo ; extra == 'docs'
